Workbook
Name DaysNumeric: DropDowns!$D$2:$D$33
Name Gender: DropDowns!$C$2:$C$4
Name Marital: DropDowns!$P$2:$P$8
Name MonthsAbbr: DropDowns!$F$2:$F$14
Name MonthsNumeric: DropDowns!$E$2:$E$14
Name Nationality: DropDowns!$A$2:$A$157
Name NationalityID: DropDowns!#REF!
Name PublicFunds: DropDowns!$Q$2:$Q$18
Name Recruited: DropDowns!$N$2:$N$8
Name Relationship: DropDowns!$L$2:$L$7
Name Status: DropDowns!$M$2:$M$16
Name Title: DropDowns!$O$2:$O$9
Name YearsAll: DropDowns!$H$2:$H$73
Name YearsFuture: DropDowns!$J$2:$J$11
Name YearsPast: DropDowns!$I$2:$I$23
Name YesNo: DropDowns!$B$2:$B$4

Sheet Proforma
J1: IMMIGRATION MANAGEMENT FORM | AU1: Date completed
A3: Company
A5: HR Contact
A6: PLEASE READ THESE INSTRUCTIONS
A7: Part A of this form is to be completed by the applicant; Part B by the HR/Hiring Manager.
A8: PLEASE ENSURE THE FORM IS COMPLETED IN FULL TO ENSURE A COMPREHENSIVE AND ACCURATE ASSESSMENT
A9: Part A - Applicant Details
A10: Full name (as in passport) | J10: Family name | AH10: Other names
J11: Meenakshi Thiyagarajan
A12: Nationality | W12: Have you ever held another nationality? | AN12: Date of birth
A13: Place of birth | H13: Tiruchirappalli | AJ13: Country of birth
A16: Title | J16: Marital status | AF16: Gender | AO16: National Insurance number | AX16: TK131840A
A18: Contact Details
A19: Phone | T19: Email | X19: akshimeena284@gmail.com | AO19: Current Location
A21: Mobile no. | G21: 7440768302 | X21: Alternate email address (if applicable) | AK21: menakshi2023@gmail.com
A22: Current Business Address | AE22: Current Residential Address
A23: 58 Ely Way, Luton | AE23: 58 Ely Way, Luton
A28: Post code | G28: LU4 9QN | AE28: Post code | AK28: LU4 9QN
A30: Date started living at this address
A32: Immigration History
A33: Have you ever lived in Northern Ireland? | Z33: If yes, please enter your address(es) in Northern Ireland
A36: Have you ever been refused entry into, permission to remain in or deported from the UK? | AU36: If yes, please give details
A39: Have you previously worked in the UK? | Z39: If yes, when and in what capacity?
A40: If yes, please provide a copy of the work/biometric residence permit and/or visa endorsement
A41: Current UK immigration status | AL41: Expiry date of current leave to remain
A42: Date Entry Clearance issued in this capacity (initial visa granted overseas)
A43: Educational Details
F44: Full title of degree, as | O44: Dates of study | Y44: Date | AD44: Full name, address & country | AP44: Subject | AV44: Grade (if | BA44: Was this
F45: stated on the degree | Y45: of | AD45: of awarding institution | AV45: applicable) | BA45: degree taught
F46: certificate | O46: Start | T46: End | Y46: award | BA46: in English?
A47: Degree | F47: Bachelor of Science | AD47: Bharathidasan University, Palakalaiperur, Tiruchirappalli 620024 | AP47: Industrial Electronics | AV47: Grade A
A48: Master | F48: Master of Computer Applications | AD48: Bharathidasan University, Tiruchirappalli 620024 | AP48: Computer Science
A49: Doctorate
A51: Professional memberships
A53: Do you have a NARIC assessment certificate to confirm the UK academic equivalence of this qualification?
A54: Name and address of current employer | Y54: Nature of business | AM54: Job title | AW54: Start date
A55: AMISOFT TECHNOLOGIES LIMITED JUBILEE HOUSE, THE DRIVE, GREAT WARLEY, BRENTWOOD CM13 3FR | Y55: IT | AM55: Software Tester
A56: Previous employment history for the past five years
A57: Company name and address | Y57: Nature of business | AM57: Job title | AW57: Dates
AW58: Start | BB58: End
A59: MSYS Technologies ASV Chandilya Towers, 8th Floor, Thoraipakkam, Chennai - 600096 | Y59: IT | AM59: SDET Engineer[July 2020 - Feb 2023]
A60: Indium Software (India) Private Limited No.64 (Old N.143), Eldams Road, Teynampet, Chennai – 600 018 | Y60: IT | AM60: Automation Analyst [ Aug 2018 - March 2020]
A61: Mastek Ltd., Mastek Millennium Centre Millenium Business Park, Mahape TTC Navi Mumbai – 400 710 | Y61: IT | AM61: Automation Analyst [ Apr 2012 - Apr 2016]
A62: Other Information
A63: Confirm your earliest available date to commence the sponsored employment in the UK?
A65: Have you ever been charged with any criminal or civil offence? | AJ65: If yes, please give details
A68: if you are in the UK, do you receive any public funds? | AG68: If yes, please give details
A69: Public funds include all items listed in this drop-down:
A70: Are your dependants (I.e. spouse and/or children) accompanying you to the UK? | AR70: If yes, please give details
A71: (If more dependants, please complete details on a separate sheet)
A72: Name | Z72: Relationship | AI72: Date of birth | AT72: Nationality
A73: 1.
C74: Place of birth (city/town etc.) | AC74: Gender | AL74: Country of birth
A76: 2.
C77: Place of birth (city/town etc.) | AC77: Gender | AL77: Country of birth
A79: 3.
C80: Place of birth (city/town etc.) | AC80: Gender | AL80: Country of birth
A82: 4.
C83: Place of birth (city/town etc.) | AC83: Gender | AL83: Country of birth
A85: 5.
C86: Place of birth (city/town etc.) | AC86: Gender | AL86: Country of birth
A87: IMPORTANT NOTE: Please ensure that the information contained within Part A of the form is accurate. The information provided in this proforma will be used in support of an application for you to enter or remain in the UK and as such will be reviewed by the UK Border Agency. The information may also be used by other Government agencies in supporting immigration control into the UK. Finally it may also be provided to your prospective UK employer as part of an overall audit trail. Data will not be used for promotions or shared with any other organisation.
A88: Part B - To be completed by HR/Hiring Manager
A89: Cost Centre/ Budget Code/ Department | S89: PO No | AP89: Employee ID
A91: Will the individual be based at a client site? | AD91: If so, please give address and details
A93: PLEASE NOTE: If yes, in these circumstances a service agreement is normally required by the UKBA
A94: Please attach a detailed Job Specification including a full list of duties and responsibilities of the role and the candidate specification for the role, including educational, skills and experience requirements. If such a Job Specification does not exist please complete the template below.
A95: Job Title | AE95: Location
A97: Department | AE97: Reporting to
A99: Duties will include
A101: Candidate specification
A103: How was the applicant recruited?
A105: Additional comments/ information
A107: Start and end date of assignment. Permanent leave end date blank | AB107: End | AP107: Proposed UK salary GBP per annum
A109: Is the role permanent? | AN109: Proposed weekly hours
A111: Additional Annual Allowances (where applicable)
A112: Please detail individual amounts e.g. Living Allowance, Housing Allowance, Annual Bonus etc.
A113: Allowances
A115: Are you prepared to indemnify the applicant against the maintenance requirement? See Note
A116: NB: ‘A’ rated sponsors may indemnify the applicant against the Tier 2 funds requirement by agreeing to assist with maintenance and accommodation for the first month of employment where necessary. The sponsor may limit this amount of the undertaking but any limit must be at least £900.
A117: IMPORTANT NOTE:
A118: The forwarding of this request constitutes an instruction to process an application for a Certificate of Sponsorship, entry clearance or permission to stay in the UK.
A119: This is also formal authorisation to assign a Certificate of Sponsorship provided the individual named in this authorisation qualifies for the issue of such a certificate.
A120: This authorisation is also acceptance of our terms and conditions and all fees associated with the application including all third party costs including but not limited to advertising fees, verification fees and courier fees.
BF121: Version 11: June '15 - Excel 2003

Sheet DropDowns
A1: Nationality | B1: Yes/No | C1: Gender | D1: Date DD | E1: Month MM | F1: Month Abbr | G1: Month Full | H1: Year YY | I1: Year YY3 | J1: Fut Yr | K1: Year YYYY | L1: Relationship | M1: Status | N1: Recruitment Method | O1: Title | P1: Marital | Q1: Public Funds
A2: Please select | B2: ? | C2: Select | D2: DD | E2: MM | F2: MMM | G2: Month | H2: YY | I2: YY | J2: YY | K2: YYYY | L2: Select | M2: Please Select | N2: Please select | O2: Select | P2: Please select | Q2: - Public Funds list -
A3: Afghanistan | B3: No | C3: Female | D3: 01 | E3: 01 | F3: Jan | G3: January | H3: 50 | I3: 0 | J3: 15 | K3: 1950 | L3: Child | M3: Tier 1 Post Study Worker | N3: Existing employee overseas | O3: Mr | P3: Married or civil partner | Q3: Attendance Allowance
A4: Albania | B4: Yes | C4: Male | D4: 02 | E4: 02 | F4: Feb | G4: February | H4: 51 | I4: 01 | J4: 16 | K4: 1951 | L4: Domestic | M4: Tier 1 (General) Migrant | N4: Recommended | O4: Mrs | P4: Widowed or surviving civil partner | Q4: Carer's Allowance
A5: Algeria | D5: 03 | E5: 03 | F5: Mar | G5: March | H5: 52 | I5: 02 | J5: 17 | K5: 1952 | L5: Father | M5: Tier 2 General Migrant | N5: External company website | O5: Miss | P5: Divorced or dissolved civil partnership | Q5: Child Benefit
A6: Andorra | D6: 04 | E6: 04 | F6: Apr | G6: April | H6: 53 | I6: 03 | J6: 18 | K6: 1953 | L6: Mother | M6: Tier 2 ICT Migrant | N6: Headhunted | O6: Ms | P6: Single | Q6: Child Tax Credit
A7: Argentina | D7: 05 | E7: 05 | F7: May | G7: May | H7: 54 | I7: 04 | J7: 19 | K7: 1954 | L7: Spouse/Partner | M7: Tier 4 Student | N7: Agency | O7: Rev | P7: Unmarried partner | Q7: Council Tax Benefit
A8: Armenia | D8: 06 | E8: 06 | F8: Jun | G8: June | H8: 55 | I8: 05 | J8: 20 | K8: 1955 | M8: Tier 5 Youth Mobility | N8: Milk round | O8: Dr | P8: Separated or separation order | Q8: Disability Living Allowance
A9: Australia | D9: 07 | E9: 07 | F9: Jul | G9: July | H9: 56 | I9: 06 | J9: 21 | K9: 1956 | M9: Marriage | O9: Other | Q9: Health in Pregnancy Grant
A10: Austria | D10: 08 | E10: 08 | F10: Aug | G10: August | H10: 57 | I10: 07 | J10: 22 | K10: 1957 | M10: Work Permit Holder | Q10: Housing and Homelessness Assistance
A11: Azerbaijan | D11: 09 | E11: 09 | F11: Sep | G11: September | H11: 58 | I11: 08 | J11: 23 | K11: 1958 | M11: Sole Representative | Q11: Housing Benefit
A12: Bahamas | D12: 10 | E12: 10 | F12: Oct | G12: October | H12: 59 | I12: 09 | K12: 1959 | M12: Exempt | Q12: Income-Based Jobseeker's Allowance
A13: Bahrain | D13: 11 | E13: 11 | F13: Nov | G13: November | H13: 60 | I13: 10 | K13: 1960 | M13: UK Ancestry | Q13: Income Related Employment & Support Allowance
A14: Bangladesh | D14: 12 | E14: 12 | F14: Dec | G14: December | H14: 61 | I14: 11 | K14: 1961 | M14: Dependant | Q14: Income Support
A15: Barbados | D15: 13 | H15: 62 | I15: 12 | K15: 1962 | M15: Other | Q15: Severe Disablement Allowance
A16: Belarus | D16: 14 | H16: 63 | I16: 13 | K16: 1963 | M16: None - Out of UK | Q16: Social Fund Payment
A17: Belgium | D17: 15 | H17: 64 | I17: 14 | K17: 1964 | Q17: State Pension Credit
A18: Belize | D18: 16 | H18: 65 | I18: 15 | K18: 1965 | Q18: Working Tax Credit
A19: Benin | D19: 17 | H19: 66 | I19: 16 | K19: 1966
A20: Bolivia | D20: 18 | H20: 67 | I20: 17 | K20: 1967
A21: Bosnia | D21: 19 | H21: 68 | I21: 18 | K21: 1968
A22: Botswana | D22: 20 | H22: 69 | I22: 19 | K22: 1969
A23: Brazil | D23: 21 | H23: 70 | I23: 20 | K23: 1970
A24: British National Overseas | D24: 22 | H24: 71 | K24: 1971
A25: British Overseas Citizen | D25: 23 | H25: 72 | K25: 1972
A26: British Protected Person | D26: 24 | H26: 73 | K26: 1973
A27: Brunei | D27: 25 | H27: 74 | K27: 1974
A28: Bulgaria | D28: 26 | H28: 75 | K28: 1975
A29: Cameroon | D29: 27 | H29: 76 | K29: 1976
A30: Canada | D30: 28 | H30: 77 | K30: 1977
A31: Chile | D31: 29 | H31: 78 | K31: 1978
A32: China | D32: 30 | H32: 79 | K32: 1979
A33: Colombia | D33: 31 | H33: 80 | K33: 1980
A34: Congo | H34: 81 | K34: 1981
A35: Costa Rica | H35: 82 | K35: 1982
A36: Croatia | H36: 83 | K36: 1983
A37: Cuba | H37: 84 | K37: 1984
A38: Cyprus | H38: 85 | K38: 1985
A39: Czechoslovakia | H39: 86 | K39: 1986
A40: Denmark | H40: 87 | K40: 1987
A41: Dominican Republic | H41: 88 | K41: 1988
A42: Ecuador | H42: 89 | K42: 1989
A43: Egypt | H43: 90 | K43: 1990
A44: Eire | H44: 91 | K44: 1991
A45: El Salvador | H45: 92 | K45: 1992
... A73: Jamaica | H73: 20 | K73: 2020
A74: Japan
A75: Jordan
A76: Kazakhstan
A77: Kenya
A78: Korea South
A79: Kosovo
A80: Kuwait
A81: Kyrgyzstan
A82: Latvia
A83: Lebanon
A84: Liberia
A85: Libya
... A157: Zimbabwe

Sheet DataSheet
A1: Field Name | B1: Value
A2: FormID | B2: IM v11
A3: CompanyName | B3: =Proforma!G3 -> 0
A4: HRContact | B4: =Proforma!G5 -> 0
A5: CompletionDay | B5: =OFFSET(DropDowns!$D$1,C5,0) -> DD | C5: 1
A6: CompletionMonth | B6: =OFFSET(DropDowns!$E$1,C6,0) -> MM | C6: 1
A7: CompletionYear | B7: =OFFSET(DropDowns!$J$1,C7,0) -> YY | C7: 1
A8: FamilyName | B8: =Proforma!J11 -> Meenakshi Thiyagarajan
A9: OtherNames | B9: =Proforma!AH11 -> 0
A10: Nationality | B10: =OFFSET(DropDowns!$A$1,C10,0) -> India | C10: 64
A11: MoreNationalityYesNo | B11: =OFFSET(DropDowns!$B$1,C11,0) -> No | C11: 2
A12: BirthDay | B12: =OFFSET(DropDowns!$D$1,C12,0) -> 08 | C12: 9
A13: BirthMonth | B13: =OFFSET(DropDowns!$E$1,C13,0) -> 04 | C13: 5
A14: BirthYear | B14: =OFFSET(DropDowns!$H$1,C14,0) -> 79 | C14: 31
A15: BirthPlace | B15: =Proforma!H13 -> Tiruchirappalli
A16: BirthCountry | B16: =OFFSET(DropDowns!$A$1,C16,0) -> India | C16: 64
A17: Title | B17: =OFFSET(DropDowns!$O$1,C17,0) -> Miss | C17: 4
A18: MaritalStatus | B18: =OFFSET(DropDowns!$P$1,C18,0) -> Single | C18: 5
A19: Gender | B19: =OFFSET(DropDowns!$C$1,C19,0) -> Female | C19: 2
A20: Telephone | B20: =Proforma!E19 -> 0
A21: Email | B21: =Proforma!X19 -> akshimeena284@gmail.com
A22: CurrentLocation | B22: =OFFSET(DropDowns!$A$1,C22,0) -> United Kingdom | C22: 147
A23: Mobile | B23: =Proforma!G21 -> 7440768302
A24: EmailAlternate | B24: =Proforma!AK21 -> menakshi2023@gmail.com
A25: BusinessAddress | B25: =Proforma!A23 -> 58 Ely Way, Luton
A26: BusinessPostcode | B26: =Proforma!G28 -> LU4 9QN
A27: ResidentialAddress | B27: =Proforma!AE23 -> 58 Ely Way, Luton
A28: ResidentialPostcode | B28: =Proforma!AK28 -> LU4 9QN
A29: EarliestStartDay | B29: =OFFSET(DropDowns!$D$1,C29,0) -> DD | C29: 1
A30: EarliestStartMonth | B30: =OFFSET(DropDowns!$E$1,C30,0) -> MM | C30: 1
A31: EarliestStartYear | B31: =OFFSET(DropDowns!$J$1,C31,0) -> YY | C31: 1
A32: LivingStartDay | B32: =OFFSET(DropDowns!$D$1,C32,0) -> 05 | C32: 6
A33: LivingStartMonth | B33: =OFFSET(DropDowns!$E$1,C33,0) -> 02 | C33: 3
A34: LivingStartYear | B34: =OFFSET(DropDowns!$I$1,C34,0) -> YY | C34: 1
A35: NIYesNo | B35: =OFFSET(DropDowns!$B$1,C35,0) -> No | C35: 2
A36: NIDetails | B36: =Proforma!A35 -> 0
A37: RefusedYesNo | B37: =OFFSET(DropDowns!$B$1,C37,0) -> No | C37: 2
A38: RefusedDetails | B38: =Proforma!A37 -> 0
A39: WorkedUKYesNo | B39: =OFFSET(DropDowns!$B$1,C39,0) -> No | C39: 2
A40: ImmigrationStatus | B40: =OFFSET(DropDowns!$M$1,C40,0) -> Tier 2 General Migrant | C40: 4
A41: ExpiryDay | B41: =OFFSET(DropDowns!$D$1,C41,0) -> 13 | C41: 14
A42: ExpiryMonth | B42: =OFFSET(DropDowns!$E$1,C42,0) -> 03 | C42: 4
A43: ExpiryYear | B43: =OFFSET(DropDowns!$J$1,C43,0) -> YY | C43: 1
A44: ClearanceDay | B44: =OFFSET(DropDowns!$D$1,C41,0) -> 13 | C44: 6
A45: ClearanceMonth | B45: =OFFSET(DropDowns!$E$1,C42,0) -> 03 | C45: 3
A46: ClearanceYear | B46: =OFFSET(DropDowns!$I$1,C43,0) -> YY | C46: 1
A47: DegreeTitle | B47: =Proforma!F47 -> Bachelor of Science
A48: DegreeStartMonth | B48: =OFFSET(DropDowns!$F$1,C48,0) -> Nov | C48: 12
A49: DegreeStartYear | B49: =OFFSET(DropDowns!$I$1,C49,0) -> YY | C49: 1
A50: DegreeEndMonth | B50: =OFFSET(DropDowns!$F$1,C50,0) -> Apr | C50: 5
A51: DegreeEndYear | B51: =OFFSET(DropDowns!$I$1,C51,0) -> 20 | C51: 22
A52: DegreeAwardMonth | B52: =OFFSET(DropDowns!$F$1,C52,0) -> MMM | C52: 1
A53: DegreeAwardYear | B53: =OFFSET(DropDowns!$I$1,C53,0) -> 20 | C53: 22
A54: DegreeInstitution | B54: =Proforma!AD47 -> Bharathidasan University, Palakalaiperur, Tiruchirappalli 620024
A55: DegreeSubject | B55: =Proforma!AP47 -> Industrial Electronics
A56: DegreeGrade | B56: =Proforma!AV47 -> Grade A
A57: DegreeInEnglish | B57: =OFFSET(DropDowns!$B$1,C57,0) -> Yes | C57: 3
A58: MasterTitle | B58: =Proforma!F48 -> Master of Computer Applications
A59: MasterStartMonth | B59: =OFFSET(DropDowns!$F$1,C59,0) -> Nov | C59: 12
A60: MasterStartYear | B60: =OFFSET(DropDowns!$I$1,C60,0) -> YY | C60: 1
A61: MasterEndMonth | B61: =OFFSET(DropDowns!$F$1,C61,0) -> Apr | C61: 5
A62: MasterEndYear | B62: =OFFSET(DropDowns!$I$1,C62,0) -> 04 | C62: 6
A63: MasterAwardMonth | B63: =OFFSET(DropDowns!$F$1,C63,0) -> MMM | C63: 1
A64: MasterAwardYear | B64: =OFFSET(DropDowns!$I$1,C64,0) -> YY | C64: 1
A65: MasterInstitution | B65: =Proforma!AD48 -> Bharathidasan University, Tiruchirappalli 620024
A66: MasterSubject | B66: =Proforma!AP48 -> Computer Science
A67: MasterGrade | B67: =Proforma!AV48 -> 0
A68: MasterInEnglish | B68: =OFFSET(DropDowns!$B$1,C68,0) -> Yes | C68: 3
A69: DoctorateTitle | B69: =Proforma!F49 -> 0
A70: DoctorateStartMonth | B70: =OFFSET(DropDowns!$F$1,C70,0) -> MMM | C70: 1
A71: MasterStartYear | B71: =OFFSET(DropDowns!$I$1,C71,0) -> YY | C71: 1
A72: DoctorateEndMonth | B72: =OFFSET(DropDowns!$F$1,C72,0) -> MMM | C72: 1
A73: DoctorateEndYear | B73: =OFFSET(DropDowns!$I$1,C73,0) -> YY | C73: 1
A74: DoctorateAwardMonth | B74: =OFFSET(DropDowns!$F$1,C74,0) -> MMM | C74: 1
A75: DoctorateAwardYear | B75: =OFFSET(DropDowns!$I$1,C75,0) -> YY | C75: 1
A76: DoctorateInstitution | B76: =Proforma!AD49 -> 0
A77: DoctorateSubject | B77: =Proforma!AP49 -> 0
A78: DoctorateGrade | B78: =Proforma!AV49 -> 0
A79: DoctorateEnglish | B79: =OFFSET(DropDowns!$B$1,C79,0) -> ? | C79: 1
A80: ProfMemberDetails | B80: =Proforma!I51 -> 0
A81: NARICYesNo | B81: =OFFSET(DropDowns!$B$1,C81,0) -> Yes | C81: 3
A82: CurrentEmployer | B82: =Proforma!A55 -> AMISOFT TECHNOLOGIES LIMITED JUBILEE HOUSE, THE DRIVE, GREAT WARLEY, BRENTWOOD CM13 3FR
A83: CurrentBusiness | B83: =Proforma!Y55 -> IT
A84: CurrentJobTitle | B84: =Proforma!AM55 -> Software Tester
A85: CurrentStartMonth | B85: =OFFSET(DropDowns!$F$1,C85,0) -> Feb | C85: 3
A86: CurrentStartYear | B86: =OFFSET(DropDowns!$I$1,C86,0) -> YY | C86: 1
A87: PreviousEmployer1 | B87: =Proforma!A59 -> MSYS Technologies ASV Chandilya Towers, 8th Floor, Thoraipakkam, Chennai - 600096
A88: PreviousBusiness1 | B88: =Proforma!Y59 -> IT
A89: PreviousJobTitle1 | B89: =Proforma!AM59 -> SDET Engineer[July 2020 - Feb 2023]
A90: PreviousStartMonth1 | B90: =OFFSET(DropDowns!$F$1,C90,0) -> Jul | C90: 8
A91: PreviousStartYear1 | B91: =OFFSET(DropDowns!$I$1,C91,0) -> 20 | C91: 22
A92: PreviousEndMonth1 | B92: =OFFSET(DropDowns!$F$1,C92,0) -> MMM | C92: 1
A93: PreviousEndYear1 | B93: =OFFSET(DropDowns!$I$1,C93,0) -> YY | C93: 1
A94: PreviousEmployer2 | B94: =Proforma!A60 -> Indium Software (India) Private Limited No.64 (Old N.143), Eldams Road, Teynampet, Chennai – 600 018
A95: PreviousBusiness2 | B95: =Proforma!Y60 -> IT
A96: PreviousJobTitle2 | B96: =Proforma!AM60 -> Automation Analyst [ Aug 2018 - March 2020]
A97: PreviousStartMonth2 | B97: =OFFSET(DropDowns!$F$1,C97,0) -> MMM | C97: 1
A98: PreviousStartYear2 | B98: =OFFSET(DropDowns!$I$1,C98,0) -> YY | C98: 1
A99: PreviousEndMonth2 | B99: =OFFSET(DropDowns!$F$1,C99,0) -> MMM | C99: 1
A100: PreviousEndYear2 | B100: =OFFSET(DropDowns!$I$1,C100,0) -> YY | C100: 1
...
